README.md
setup.py
api/__init__.py
api/apiclient.py
api/auth.py
api/conf.py
api/param.py
api/response.py
api/util.py
rcs_sdk.egg-info/PKG-INFO
rcs_sdk.egg-info/SOURCES.txt
rcs_sdk.egg-info/dependency_links.txt
rcs_sdk.egg-info/top_level.txt