Metadata-Version: 1.1
Name: rcs-sdk
Version: 1.0.1
Summary: 大汉三通
Home-page: https://gitee.com/dahanrcs/sdk-python
Author: 8526
Author-email: UNKNOWN
License: UNKNOWN
Platform: UNKNOWN
Classifier: Programming Language :: Python :: 3
Classifier: License :: OSI Approved :: MIT License
Classifier: Operating System :: OS Independent
